falcone/__init__.py
falcone-0.0.0a0.dist-info/LICENSE
falcone-0.0.0a0.dist-info/METADATA
falcone-0.0.0a0.dist-info/WHEEL
falcone-0.0.0a0.dist-info/top_level.txt
falcone-0.0.0a0.dist-info/RECORD
